nikoiskool/__init__.py
nikoiskool/niko.py
nikomadekoolthing-0.0.1.dist-info/LICENSE.txt
nikomadekoolthing-0.0.1.dist-info/METADATA
nikomadekoolthing-0.0.1.dist-info/WHEEL
nikomadekoolthing-0.0.1.dist-info/top_level.txt
nikomadekoolthing-0.0.1.dist-info/RECORD
