Metadata-Version: 2.1
Name: nikomadekoolthing
Version: 0.0.1
Summary: dis kool thing
Home-page: https://github.com/pypa/sampleproject
Author: niko
Author-email: nikolai.malde@gmail.com
License: UNKNOWN
Project-URL: Tracker, https://github.com/pypa/sampleproject/issues
Platform: UNKNOWN
Classifier: Programming Language :: Python :: 3
Classifier: License :: OSI Approved :: MIT License
Classifier: Operating System :: OS Independent
Requires-Python: >=3.6
License-File: LICENSE.txt
